mocap_base/__init__.py
mocap_base/axengine_1768914201_2016154719.py
mocap_base/interfaces/Mocap.proto
mocap_base/interfaces/Mocap_pb2.py
mocap_base/interfaces/__init__.py
mocap_base/interfaces/abstractions.py
mocap_base/interfaces/actor_profile.py
mocap_base/interfaces/kalman_types.py
mocap_base/interfaces/kps_seq_util.py
mocap_base/interfaces/obj_seq.py
mocap_base/interfaces/pose_conversion.py
mocap_base/interfaces/pose_types.py
mocap_base/interfaces/pose_utils.py
mocap_base/interfaces/structures.py
mocap_base/mc_process_take.py
mocap_base/operations/__init__.py
mocap_base/operations/execution.py
mocap_base/operations/ops_base.py
mocap_base/operations/ops_impl.py
mocap_base/operations/registry.py
mocap_base/protobuf/MocapFeed.proto
mocap_base/protobuf/MocapFeed_pb2.py
mocap_base/protobuf/MocapFeed_pb2_grpc.py
mocap_base/protobuf/__init__.py
mocap_base/protobuf/calib_export.py
mocap_base/protobuf/depth_map_export.py
mocap_base/protobuf/export_protobuf_data.py
mocap_base/protobuf/gen_extra_data.py
mocap_base/protobuf/odometry_export.py
mocap_base/protobuf/poses2d_export.py
mocap_base/settings/pipeline_log_settings.yaml
mocap_base/utils/Mocap.proto
mocap_base/utils/Mocap_pb2.py
mocap_base/utils/Visualizations/__init__.py
mocap_base/utils/Visualizations/run_monocular_visualizations.py
mocap_base/utils/Visualizations/visualize_2d_kps.py
mocap_base/utils/Visualizations/visualize_3d_skeletons.py
mocap_base/utils/Visualizations/visualize_depth_data.py
mocap_base/utils/__init__.py
mocap_base/utils/actor_profile_util.py
mocap_base/utils/boto3_util.py
mocap_base/utils/calib_ex_flir_record.py
mocap_base/utils/calib_extrinsic_run_prep.py
mocap_base/utils/calib_intrinsic_flir.py
mocap_base/utils/calib_intrinsic_flir_real_time.py
mocap_base/utils/calib_pkl_conversion.py
mocap_base/utils/calib_undistort.py
mocap_base/utils/camera_ops.py
mocap_base/utils/crop_bb_images.py
mocap_base/utils/default_logger.py
mocap_base/utils/drawing_opencv.py
mocap_base-2.7.2.dist-info/METADATA
mocap_base-2.7.2.dist-info/WHEEL
mocap_base-2.7.2.dist-info/entry_points.txt
mocap_base-2.7.2.dist-info/RECORD
