Metadata-Version: 2.1
Name: mocap-base
Version: 2.7.2
Summary: Base package for mocap pipeline
Author: Move.ai
Author-email: info@move.ai
Requires-Python: >=3.10,<4.0
Classifier: Programming Language :: Python :: 3
Classifier: Programming Language :: Python :: 3.10
Classifier: Programming Language :: Python :: 3.11
Classifier: Programming Language :: Python :: 3.12
Requires-Dist: easydict (>=1.10,<2.0)
Requires-Dist: grpcio (>=1.56.2,<2.0.0)
Requires-Dist: hiyapyco (>=0.5.1,<0.6.0)
Requires-Dist: imageio (>=2.31.1,<3.0.0)
Requires-Dist: mocap-settings (>=1.16.1,<2.0.0)
Requires-Dist: numpy (>=1.24.3,<2.0.0)
Requires-Dist: opencv-python (>=4.8,<5.0)
Requires-Dist: protobuf (>=3.19.6,<4.0.0)
Requires-Dist: pydantic (>=2.4,<3.0)
Requires-Dist: pydantic-yaml (>=1.1.1,<2.0.0)
Requires-Dist: scipy (>=1.10.1,<2.0.0)
Requires-Dist: tqdm (>=4.66.1,<5.0.0)
